cli/__init__.py
cli/cli.py
cli/command.py
cli/interactive.py
cli/menu.py
cli/utils.py
vencordthemer_simplecli-0.1.0.dist-info/METADATA
vencordthemer_simplecli-0.1.0.dist-info/WHEEL
vencordthemer_simplecli-0.1.0.dist-info/top_level.txt
vencordthemer_simplecli-0.1.0.dist-info/RECORD
