Metadata-Version: 2.4
Name: vencordthemer-simplecli
Version: 0.1.0
Summary: A simple framework for building interactive CLI menus in Python
Author: VencordThemer
Author-email: vencordthemer@users.noreply.github.com
Requires-Python: >=3.6
Dynamic: author
Dynamic: author-email
Dynamic: requires-python
Dynamic: summary
